{"stats":{"minecraft:picked_up":{"gobber2seeds:gobber2_seed_nether":9,"minecraft:stone":6,"minecraft:wheat_seeds":1,"minecraft:oxeye_daisy":1},"minecraft:custom":{"minecraft:time_since_rest":13271,"minecraft:play_time":13271,"minecraft:walk_one_cm":11009,"minecraft:jump":3,"minecraft:leave_game":10,"minecraft:time_since_death":13271,"minecraft:total_world_time":14837},"minecraft:used":{"gobber2seeds:gobber2_seed":2,"minecraft:water_bucket":1,"gobber2seeds:gobber2_seed_nether":4,"minecraft:deepslate_iron_ore":3,"minecraft:grass_block":3,"gobber2seeds:gobber2_seed_end":4,"minecraft:diamond_hoe":8,"minecraft:bone_meal":33,"minecraft:budding_amethyst":2},"minecraft:mined":{"minecraft:grass":10,"gobber2seeds:gobber2_plant_end":2,"gobber2seeds:gobber2_plant_nether":4,"minecraft:tall_grass":1,"gobber2seeds:gobber2_plant":2,"minecraft:oxeye_daisy":1}},"DataVersion":2865}